{"mean":{"confidence_interval":{"confidence_level":0.99,"lower_bound":43524.40758371984,"upper_bound":43904.5029069395},"point_estimate":43703.62723960884,"standard_error":73.7094171585172},"median":{"confidence_interval":{"confidence_level":0.99,"lower_bound":43371.80785123967,"upper_bound":43773.54583333333},"point_estimate":43586.52469135802,"standard_error":81.65460329874949},"median_abs_dev":{"confidence_interval":{"confidence_level":0.99,"lower_bound":646.9451639243192,"upper_bound":1011.13783159721},"point_estimate":824.7947646786166,"standard_error":68.33890173124401},"slope":{"confidence_interval":{"confidence_level":0.99,"lower_bound":43351.24050526811,"upper_bound":43664.56381580849},"point_estimate":43504.906371291916,"standard_error":60.37402342998016},"std_dev":{"confidence_interval":{"confidence_level":0.99,"lower_bound":773.580078910673,"upper_bound":1339.305123606251},"point_estimate":1044.942959395619,"standard_error":113.3965123791009}}